MANIFEST.in
README.txt
setup.cfg
setup.py
docs/HISTORY.txt
horae/__init__.py
horae.ticketing.egg-info/PKG-INFO
horae.ticketing.egg-info/SOURCES.txt
horae.ticketing.egg-info/dependency_links.txt
horae.ticketing.egg-info/entry_points.txt
horae.ticketing.egg-info/namespace_packages.txt
horae.ticketing.egg-info/not-zip-safe
horae.ticketing.egg-info/requires.txt
horae.ticketing.egg-info/top_level.txt
horae/ticketing/__init__.py
horae/ticketing/configuration.py
horae/ticketing/configure.zcml
horae/ticketing/events.py
horae/ticketing/extenders.py
horae/ticketing/interfaces.py
horae/ticketing/properties.py
horae/ticketing/ticketing.py
horae/ticketing/user.py
horae/ticketing/utils.py
horae/ticketing/viewlets.py
horae/ticketing/views.py
horae/ticketing/vocabulary.py
horae/ticketing/locales/horae.ticketing.pot
horae/ticketing/locales/de/LC_MESSAGES/horae.ticketing.mo
horae/ticketing/locales/de/LC_MESSAGES/horae.ticketing.po
horae/ticketing/templates/description.cpt
horae/ticketing/templates/name.cpt
horae/ticketing/templates/nestedlist.cpt
horae/ticketing/templates/nestedlist_recurse.cpt
horae/ticketing/templates/ticket.cpt
horae/ticketing/templates/user.cpt