Metadata-Version: 1.0
Name: horae.ticketing
Version: 1.0a1
Summary: Implements the different models and their hierarchy for the Horae resource planning system
Home-page: UNKNOWN
Author: Simon Kaeser
Author-email: skaeser@gmail.com
License: GPL
Platform: UNKNOWN
Classifier: Programming Language :: Python
Classifier: Topic :: Software Development :: Libraries :: Python Modules
